[
    {
        "id": "Brazil",
        "country": "Brasil",
        "indicadores": [
            "Planejado vs Realizado JGS",
            "Planejado vs Realizado WSB",
            "Planejado vs Realizado EOL - Gerador",
            "Planejado vs Realizado ALT",
            "Stocks JGS Total Inventory",
            "Stocks WSB Total Inventory",
            "Stocks HISA Total Inventory",
            "Stocks EOL Total Inventory"
        ]
    },
    {
        "id": "United States",
        "country": "Estados Unidos",
        "indicadores": [
            "Planejado vs Realizado WEM",
            "Stocks WEM Total Inventory"
        ]
    },
    {
        "id": "India",
        "country": "Índia",
        "indicadores": [
            "Planejado vs Realizado WII",
            "Stocks WII Total Inventory"
        ]
    },
    {
        "id": "South Africa",
        "country": "África do Sul",
        "indicadores": []
    },
    {
        "id": "Portugal",
        "country": "Portugal",
        "indicadores": [
            "Stocks WPT Total Inventory"
        ]
    },
    {
        "id": "China",
        "country": "China",
        "indicadores": [
            "Stocks WNT Total Inventory"
        ]
    }
]